up_lib/__init__.py
up_lib/containers.py
up_lib/hookspec.py
up_lib/match.py
up_lib/plugins.py
up_lib-0.2.18.dist-info/METADATA
up_lib-0.2.18.dist-info/WHEEL
up_lib-0.2.18.dist-info/RECORD
