Metadata-Version: 2.1
Name: up-lib
Version: 0.2.18
Summary: 
Author: Julio Faerman
Author-email: 356476+faermanj@users.noreply.github.com
Requires-Python: >=3.12,<4.0
Classifier: Programming Language :: Python :: 3
Requires-Dist: docker (>=6.1.3,<7.0.0)
Requires-Dist: dynaconf[all] (>=3.2.3,<4.0.0)
Requires-Dist: pluggy (>=1.3.0,<2.0.0)
